Metadata-Version: 2.1
Name: selenium-kit
Version: 0.0.3
Summary: Selenium kit
Home-page: https://github.com/yash0307jain/selenium-kit
Author: Yash Jain
Author-email: yash0307jain@gmail.com
License: MIT
License-File: LICENSE
